locust_plugins/__init__.py
locust_plugins/_version.py
locust_plugins/connection_pools.py
locust_plugins/csvreader.py
locust_plugins/distributor.py
locust_plugins/mongoreader.py
locust_plugins/py.typed
locust_plugins/transaction_manager.py
locust_plugins/utils.py
locust_plugins/wait_time.py
locust_plugins/dashboards/Makefile
locust_plugins/dashboards/README.md
locust_plugins/dashboards/docker-compose.yml
locust_plugins/dashboards/locust-grafana/Dockerfile
locust_plugins/dashboards/locust-grafana/Makefile
locust_plugins/dashboards/locust-grafana/create_datasource.sh
locust_plugins/dashboards/locust-grafana/grafana_setup.sh
locust_plugins/dashboards/locust-grafana/import_dashboards.sh
locust_plugins/dashboards/locust-timescale/Dockerfile
locust_plugins/dashboards/locust-timescale/Makefile
locust_plugins/dashboards/locust-timescale/timescale_schema.sql
locust_plugins/dashboards/locust-timescale/zz_hypertable.sql
locust_plugins/dashboards/screenshots/main_dashboard.png
locust_plugins/dashboards/screenshots/main_dashboard_by_request_graphs.png
locust_plugins/dashboards/screenshots/requests_table.png
locust_plugins/dashboards/screenshots/scatter_plot.png
locust_plugins/dashboards/screenshots/testruns.png
locust_plugins/listeners/__init__.py
locust_plugins/listeners/appinsights.py
locust_plugins/listeners/cloudwatch.py
locust_plugins/listeners/jmeter.py
locust_plugins/listeners/timescale.py
locust_plugins/users/__init__.py
locust_plugins/users/ftp.py
locust_plugins/users/kafka.py
locust_plugins/users/mqtt.py
locust_plugins/users/playwright.py
locust_plugins/users/resource.py
locust_plugins/users/rest.py
locust_plugins/users/socketio.py
locust_plugins/users/tn3270.py
locust_plugins/users/webdriver.py
locust_plugins-4.7.0.data/scripts/locust-compose
locust_plugins-4.7.0.dist-info/licenses/LICENSE
locust_plugins-4.7.0.dist-info/METADATA
locust_plugins-4.7.0.dist-info/WHEEL
locust_plugins-4.7.0.dist-info/top_level.txt
locust_plugins-4.7.0.dist-info/RECORD
